odoo10_addon_product_variant_template_data-10.0.1.0.0-py2.7-nspkg.pth
odoo/addons/product_variant_template_data/README.rst
odoo/addons/product_variant_template_data/__init__.py
odoo/addons/product_variant_template_data/__manifest__.py
odoo/addons/product_variant_template_data/hooks.py
odoo/addons/product_variant_template_data/i18n/it.po
odoo/addons/product_variant_template_data/models/__init__.py
odoo/addons/product_variant_template_data/models/product_product.py
odoo/addons/product_variant_template_data/models/product_template.py
odoo/addons/product_variant_template_data/static/description/icon.png
odoo/addons/product_variant_template_data/tests/__init__.py
odoo/addons/product_variant_template_data/tests/test_product_variant_template_data.py
odoo/addons/product_variant_template_data/views/product_product_view.xml
odoo10_addon_product_variant_template_data-10.0.1.0.0.dist-info/DESCRIPTION.rst
odoo10_addon_product_variant_template_data-10.0.1.0.0.dist-info/METADATA
odoo10_addon_product_variant_template_data-10.0.1.0.0.dist-info/RECORD
odoo10_addon_product_variant_template_data-10.0.1.0.0.dist-info/WHEEL
odoo10_addon_product_variant_template_data-10.0.1.0.0.dist-info/metadata.json
odoo10_addon_product_variant_template_data-10.0.1.0.0.dist-info/namespace_packages.txt
odoo10_addon_product_variant_template_data-10.0.1.0.0.dist-info/top_level.txt
